odoo/addons/vh/__init__.py
odoo/addons/vh/__manifest__.py
odoo/addons/vh/models/__init__.py
odoo/addons/vh/models/vh_partner.py
odoo/addons/vh/models/vh_utils.py
odoo/addons/vh/static/src/img/vh_odoo_icon.png
odoo/addons/vh/views/vh_menu_root.xml
odoo/addons/vh/views/vh_menu_root_config.xml
odoo/addons/vh/views/vh_partner.xml
odoo12_addon_vh-12.0.0.1.1.dist-info/METADATA
odoo12_addon_vh-12.0.0.1.1.dist-info/WHEEL
odoo12_addon_vh-12.0.0.1.1.dist-info/top_level.txt
odoo12_addon_vh-12.0.0.1.1.dist-info/RECORD
