Metadata-Version: 2.1
Name: odoo12-addon-vh
Version: 12.0.0.1.1
Summary: Base for habitatge.
Home-page: https://gitlab.com/coopdevs/vertical-habitatge
Author: Coopdevs
License: UNKNOWN
Platform: UNKNOWN
Classifier: Programming Language :: Python
Classifier: Framework :: Odoo
Classifier: Framework :: Odoo :: 12.0
Requires-Python: >=3.5
Requires-Dist: odoo (<12.1dev,>=12.0a)
